setup.cfg
setup.py
bndr/__init__.py
bndr/bndr.py
bndr/bndrimg.py
bndr/bndrtxt.py
bndr/filters.py
bndr.egg-info/PKG-INFO
bndr.egg-info/SOURCES.txt
bndr.egg-info/dependency_links.txt
bndr.egg-info/entry_points.txt
bndr.egg-info/requires.txt
bndr.egg-info/top_level.txt