Metadata-Version: 1.1
Name: bndr
Version: 1.0.1
Summary: A library + command line tool to facilitate databending/glitch art.
Home-page: https://github.com/Xpktro/bndr
Author: Moisés Cachay
Author-email: xpktro@gmail.com
License: UNKNOWN
Download-URL: https://github.com/Xpktro/bndr/tarball/1.0.1
Keywords: glitch,art,databend,bend
Platform: UNKNOWN
